{
    "tara@lubra.ch": {
        "name": "Tara",
        "jahrgang": "2001",
        "kurs": "Basiskurs",
        "jahr": "2019"
    },
    "akila@lubra.ch": {
        "name": "Akila",
        "jahrgang": "2001",
        "kurs": "Basiskurs",
        "jahr": "2018"
    },
    "falena@lubra.ch": {
        "name": "Falena",
        "jahrgang": "1996",
        "kurs": "Basiskurs",
        "jahr": "2018"
    },
    "cara@lubra.ch": {
        "name": "Cara",
        "jahrgang": "1998",
        "kurs": "Basiskurs",
        "jahr": "2018"
    },
    "sdf@a.ch": {
        "name": "sdfsdf",
        "jahrgang": "1997",
        "kurs": "Futurakurs",
        "jahr": "2000"
    }
}